<?xml version="1.0" encoding="UTF-8"?>
<style-scheme id="one-light" name="Base16 One Light" version="1.0">
	<author>Daniel Pfeifer (http://github.com/purpleKarrot)</author>
	
	<!-- Scheme colors -->
	<color name="base00" value="#fafafa" />
	<color name="base01" value="#f0f0f1" />
	<color name="base02" value="#e5e5e6" />
	<color name="base03" value="#a0a1a7" />
	<color name="base04" value="#696c77" />
	<color name="base05" value="#383a42" />
	<color name="base06" value="#202227" />
	<color name="base07" value="#090a0b" />
	<color name="base08" value="#ca1243" />
	<color name="base09" value="#d75f00" />
	<color name="base0A" value="#c18401" />
	<color name="base0B" value="#50a14f" />
	<color name="base0C" value="#0184bc" />
	<color name="base0D" value="#4078f2" />
	<color name="base0E" value="#a626a4" />
	<color name="base0F" value="#986801" />
	
	<style name="text" foreground="base05" background="base00" />
	<style name="selection" background="base02" />
	<style name="cursor" foreground="base05" background="base05" />
	<style name="current-line" foreground="base03" background="base01" />
	<style name="line-numbers" foreground="base04" background="base01" />
	<style name="bracket-match" foreground="base08" background="base00" />
	<style name="search-match" foreground="base02" background="base0A" />
	
	<style name="def:function" foreground="base0D" />
	<style name="def:identifier" foreground="base08" />
	<style name="def:keyword" foreground="base0E" />
	<style name="def:number" foreground="base09" />
	<style name="def:boolean" foreground="base09" />
	<style name="def:string" foreground="base0B" />
	<style name="def:special-char" foreground="base0C" />
	<style name="def:builtin" foreground="base0C" />
	<style name="def:type" foreground="base0A" />
	<style name="def:preprocessor" foreground="" />
	<style name="def:comment" foreground="base03" />
</style-scheme>
